LICENSE
MANIFEST.in
requirements.txt
setup.py
Sheepdog.egg-info/PKG-INFO
Sheepdog.egg-info/SOURCES.txt
Sheepdog.egg-info/dependency_links.txt
Sheepdog.egg-info/requires.txt
Sheepdog.egg-info/top_level.txt
docs/changelog.rst
docs/configuration.rst
docs/index.rst
docs/quickstart.rst
docs/ssh.rst
docs/tips_and_tricks.rst
docs/code/modules.rst
docs/code/sheepdog.rst
sheepdog/__init__.py
sheepdog/client.py
sheepdog/deployment.py
sheepdog/job_file.py
sheepdog/serialisation.py
sheepdog/server.py
sheepdog/storage.py