Metadata-Version: 1.1
Name: Sheepdog
Version: 0.2.3
Summary: Shepherd GridEngine
Home-page: http://sheepdog.readthedocs.org
Author: Adam Greig
Author-email: adam@adamgreig.com
License: MIT
Platform: UNKNOWN
Classifier: Development Status :: 4 - Beta
Classifier: Intended Audience :: Developers
Classifier: Intended Audience :: Science/Research
Classifier: License :: OSI Approved :: MIT License
Classifier: Programming Language :: Python :: 2.7
Classifier: Programming Language :: Python :: 3.3
Classifier: Topic :: Scientific/Engineering
